[[{"id":{"zxjxjhh":"2024-2025-1-1","jsh":"20070033","kxh":"01","kch":"10620632","skzc":"011111111111111111000000","skxq":2,"skjc":5},"kcm":"供应链物流管理","jclxdm":"01","zxjxjhm":"2024-2025学年秋","zcsm":"2-18周","cxjc":2,"xqh":"01","xqm":"西区","jxlh":"51","jxlm":"第一公共教学楼","jash":"C109","jasm":"C109","kkxsh":"06","xsh":"06","jsm":"袁二明","xb":"女","zcdm":"2","jysh":null,"bjh":"信息2101,信息2102","xss":4,"bkskyl":66,"xf":"2","kslxdm":"01","kslxmc":"考试","kkxsm":"经管","skxq":"2"},{"id":{"zxjxjhh":"2024-2025-1-1","jsh":"20100070","kxh":"01","kch":"10620642","skzc":"011111111111111111000000","skxq":4,"skjc":7},"kcm":"先进制造技术与智能制造","jclxdm":"01","zxjxjhm":"2024-2025学年秋","zcsm":"2-18周","cxjc":2,"xqh":"01","xqm":"西区","jxlh":"51","jxlm":"第一公共教学楼","jash":"C101","jasm":"C101","kkxsh":"06","xsh":"06","jsm":"刘艳辉","xb":"女","zcdm":"3","jysh":null,"bjh":"信息2101,信息2102","xss":4,"bkskyl":66,"xf":"2","kslxdm":"01","kslxmc":"考试","kkxsm":"经管","skxq":"4"},{"id":{"zxjxjhh":"2024-2025-1-1","jsh":"20180004","kxh":"01","kch":"10610772","skzc":"011111111111111111000000","skxq":5,"skjc":5},"kcm":"电子商务C","jclxdm":"01","zxjxjhm":"2024-2025学年秋","zcsm":"2-18周","cxjc":2,"xqh":"01","xqm":"西区","jxlh":"51","jxlm":"第一公共教学楼","jash":"B407","jasm":"B407","kkxsh":"06","xsh":"06","jsm":"任映雪","xb":"女","zcdm":"3","jysh":null,"bjh":"信息2101,信息2102","xss":50,"bkskyl":20,"xf":"2","kslxdm":"01","kslxmc":"考试","kkxsm":"经管","skxq":"5"}]]