[[{"id":{"zxjxjhh":"2024-2025-1-1","jsh":"20130007","kxh":"03","kch":"10510212","skzc":"111100000000000000000000","skxq":1,"skjc":1},"kcm":"服装数字化设计与应用1","jclxdm":"01","zxjxjhm":"2024-2025学年秋","zcsm":"1-4周","cxjc":8,"xqh":"02","xqm":"东区","jxlh":"06","jxlm":"艺术学院楼","jash":"8B205","jasm":"8B205","kkxsh":"05","xsh":"05","jsm":"陈昌","xb":"男","zcdm":"3","jysh":null,"bjh":"服设2205","xss":27,"bkskyl":3,"xf":"2","kslxdm":"02","kslxmc":"考查","kkxsm":"艺术","skxq":"1"},{"id":{"zxjxjhh":"2024-2025-1-1","jsh":"20130007","kxh":"03","kch":"10510222","skzc":"000000001111111100000000","skxq":1,"skjc":1},"kcm":"服装数字化设计与应用2","jclxdm":"01","zxjxjhm":"2024-2025学年秋","zcsm":"9-16周","cxjc":4,"xqh":"02","xqm":"东区","jxlh":"06","jxlm":"艺术学院楼","jash":"8A211","jasm":"8A211","kkxsh":"05","xsh":"05","jsm":"陈昌","xb":"男","zcdm":"3","jysh":null,"bjh":"服设2205","xss":27,"bkskyl":3,"xf":"2","kslxdm":"02","kslxmc":"考查","kkxsm":"艺术","skxq":"1"},{"id":{"zxjxjhh":"2024-2025-1-1","jsh":"20230049","kxh":"03","kch":"10510004","skzc":"011110000000000000000000","skxq":2,"skjc":1},"kcm":"男西装制版与工艺","jclxdm":"01","zxjxjhm":"2024-2025学年秋","zcsm":"2-5周","cxjc":8,"xqh":"02","xqm":"东区","jxlh":"06","jxlm":"艺术学院楼","jash":"8A121","jasm":"8A121","kkxsh":"05","xsh":"05","jsm":"温少华","xb":"女","zcdm":null,"jysh":null,"bjh":"服设2205","xss":11,"bkskyl":19,"xf":"4","kslxdm":"02","kslxmc":"考查","kkxsm":"艺术","skxq":"2"},{"id":{"zxjxjhh":"2024-2025-1-1","jsh":"20230049","kxh":"03","kch":"10510004","skzc":"011110000000000000000000","skxq":5,"skjc":1},"kcm":"男西装制版与工艺","jclxdm":"01","zxjxjhm":"2024-2025学年秋","zcsm":"2-5周","cxjc":8,"xqh":"02","xqm":"东区","jxlh":"06","jxlm":"艺术学院楼","jash":"8A121","jasm":"8A121","kkxsh":"05","xsh":"05","jsm":"温少华","xb":"女","zcdm":null,"jysh":null,"bjh":"服设2205","xss":11,"bkskyl":19,"xf":"4","kslxdm":"02","kslxmc":"考查","kkxsm":"艺术","skxq":"5"},{"id":{"zxjxjhh":"2024-2025-1-1","jsh":"20050026","kxh":"03","kch":"10510053","skzc":"000000111100000000000000","skxq":2,"skjc":1},"kcm":"男装结构设计","jclxdm":"01","zxjxjhm":"2024-2025学年秋","zcsm":"7-10周","cxjc":4,"xqh":"02","xqm":"东区","jxlh":"06","jxlm":"艺术学院楼","jash":"B405","jasm":"B405","kkxsh":"05","xsh":"05","jsm":"杨丽娜","xb":"女","zcdm":"3","jysh":null,"bjh":"服设2205","xss":27,"bkskyl":8,"xf":"3","kslxdm":"02","kslxmc":"考查","kkxsm":"艺术","skxq":"2"},{"id":{"zxjxjhh":"2024-2025-1-1","jsh":"20050026","kxh":"03","kch":"10510053","skzc":"000000111100000000000000","skxq":3,"skjc":1},"kcm":"男装结构设计","jclxdm":"01","zxjxjhm":"2024-2025学年秋","zcsm":"7-10周","cxjc":4,"xqh":"02","xqm":"东区","jxlh":"06","jxlm":"艺术学院楼","jash":"B405","jasm":"B405","kkxsh":"05","xsh":"05","jsm":"杨丽娜","xb":"女","zcdm":"3","jysh":null,"bjh":"服设2205","xss":27,"bkskyl":8,"xf":"3","kslxdm":"02","kslxmc":"考查","kkxsm":"艺术","skxq":"3"},{"id":{"zxjxjhh":"2024-2025-1-1","jsh":"20050026","kxh":"03","kch":"10510053","skzc":"000000111100000000000000","skxq":4,"skjc":1},"kcm":"男装结构设计","jclxdm":"01","zxjxjhm":"2024-2025学年秋","zcsm":"7-10周","cxjc":4,"xqh":"02","xqm":"东区","jxlh":"06","jxlm":"艺术学院楼","jash":"B405","jasm":"B405","kkxsh":"05","xsh":"05","jsm":"杨丽娜","xb":"女","zcdm":"3","jysh":null,"bjh":"服设2205","xss":27,"bkskyl":8,"xf":"3","kslxdm":"02","kslxmc":"考查","kkxsm":"艺术","skxq":"4"},{"id":{"zxjxjhh":"2024-2025-1-1","jsh":"19974009","kxh":"03","kch":"10516002","skzc":"000000000000111100000000","skxq":2,"skjc":1},"kcm":"男装设计","jclxdm":"01","zxjxjhm":"2024-2025学年秋","zcsm":"13-16周","cxjc":4,"xqh":"02","xqm":"东区","jxlh":"06","jxlm":"艺术学院楼","jash":"8A318","jasm":"8A318","kkxsh":"05","xsh":"05","jsm":"李彤","xb":"男","zcdm":"3","jysh":null,"bjh":"服设2205","xss":27,"bkskyl":8,"xf":"2","kslxdm":"02","kslxmc":"考查","kkxsm":"艺术","skxq":"2"},{"id":{"zxjxjhh":"2024-2025-1-1","jsh":"19974009","kxh":"03","kch":"10516002","skzc":"000000000000111100000000","skxq":4,"skjc":1},"kcm":"男装设计","jclxdm":"01","zxjxjhm":"2024-2025学年秋","zcsm":"13-16周","cxjc":4,"xqh":"02","xqm":"东区","jxlh":"06","jxlm":"艺术学院楼","jash":"8A318","jasm":"8A318","kkxsh":"05","xsh":"05","jsm":"李彤","xb":"男","zcdm":"3","jysh":null,"bjh":"服设2205","xss":27,"bkskyl":8,"xf":"2","kslxdm":"02","kslxmc":"考查","kkxsm":"艺术","skxq":"4"},{"id":{"zxjxjhh":"2024-2025-1-1","jsh":"20000031","kxh":"04","kch":"10510192","skzc":"000000001111000000000000","skxq":2,"skjc":5},"kcm":"面料塑形","jclxdm":"01","zxjxjhm":"2024-2025学年秋","zcsm":"9-12周","cxjc":4,"xqh":"02","xqm":"东区","jxlh":"06","jxlm":"艺术学院楼","jash":"B409","jasm":"B409","kkxsh":"05","xsh":"05","jsm":"石娜娜","xb":"女","zcdm":"3","jysh":null,"bjh":"服设2205","xss":27,"bkskyl":8,"xf":"2","kslxdm":"02","kslxmc":"考查","kkxsm":"艺术","skxq":"2"},{"id":{"zxjxjhh":"2024-2025-1-1","jsh":"20000031","kxh":"04","kch":"10510192","skzc":"000000001111000000000000","skxq":5,"skjc":1},"kcm":"面料塑形","jclxdm":"01","zxjxjhm":"2024-2025学年秋","zcsm":"9-12周","cxjc":4,"xqh":"02","xqm":"东区","jxlh":"06","jxlm":"艺术学院楼","jash":"B409","jasm":"B409","kkxsh":"05","xsh":"05","jsm":"石娜娜","xb":"女","zcdm":"3","jysh":null,"bjh":"服设2205","xss":27,"bkskyl":8,"xf":"2","kslxdm":"02","kslxmc":"考查","kkxsm":"艺术","skxq":"5"},{"id":{"zxjxjhh":"2024-2025-1-1","jsh":"19950030","kxh":"03","kch":"10510572","skzc":"000000000000110000000000","skxq":2,"skjc":5},"kcm":"纤维艺术","jclxdm":"01","zxjxjhm":"2024-2025学年秋","zcsm":"13-14周","cxjc":4,"xqh":"02","xqm":"东区","jxlh":"06","jxlm":"艺术学院楼","jash":"8A513","jasm":"8A513","kkxsh":"05","xsh":"05","jsm":"宋莹","xb":"女","zcdm":"2","jysh":null,"bjh":"服设2205","xss":17,"bkskyl":18,"xf":"2","kslxdm":"02","kslxmc":"考查","kkxsm":"艺术","skxq":"2"},{"id":{"zxjxjhh":"2024-2025-1-1","jsh":"19950030","kxh":"03","kch":"10510572","skzc":"000000000000110000000000","skxq":3,"skjc":1},"kcm":"纤维艺术","jclxdm":"01","zxjxjhm":"2024-2025学年秋","zcsm":"13-14周","cxjc":4,"xqh":"02","xqm":"东区","jxlh":"06","jxlm":"艺术学院楼","jash":"8A513","jasm":"8A513","kkxsh":"05","xsh":"05","jsm":"宋莹","xb":"女","zcdm":"2","jysh":null,"bjh":"服设2205","xss":17,"bkskyl":18,"xf":"2","kslxdm":"02","kslxmc":"考查","kkxsm":"艺术","skxq":"3"},{"id":{"zxjxjhh":"2024-2025-1-1","jsh":"19950030","kxh":"03","kch":"10510572","skzc":"000000000000110000000000","skxq":3,"skjc":5},"kcm":"纤维艺术","jclxdm":"01","zxjxjhm":"2024-2025学年秋","zcsm":"13-14周","cxjc":4,"xqh":"02","xqm":"东区","jxlh":"06","jxlm":"艺术学院楼","jash":"8A513","jasm":"8A513","kkxsh":"05","xsh":"05","jsm":"宋莹","xb":"女","zcdm":"2","jysh":null,"bjh":"服设2205","xss":17,"bkskyl":18,"xf":"2","kslxdm":"02","kslxmc":"考查","kkxsm":"艺术","skxq":"3"},{"id":{"zxjxjhh":"2024-2025-1-1","jsh":"19950030","kxh":"03","kch":"10510572","skzc":"000000000000110000000000","skxq":5,"skjc":1},"kcm":"纤维艺术","jclxdm":"01","zxjxjhm":"2024-2025学年秋","zcsm":"13-14周","cxjc":4,"xqh":"02","xqm":"东区","jxlh":"06","jxlm":"艺术学院楼","jash":"8A513","jasm":"8A513","kkxsh":"05","xsh":"05","jsm":"宋莹","xb":"女","zcdm":"2","jysh":null,"bjh":"服设2205","xss":17,"bkskyl":18,"xf":"2","kslxdm":"02","kslxmc":"考查","kkxsm":"艺术","skxq":"5"},{"id":{"zxjxjhh":"2024-2025-1-1","jsh":"19974009","kxh":"01","kch":"10510522","skzc":"111100000000000000000000","skxq":3,"skjc":5},"kcm":"形象设计与应用k","jclxdm":"01","zxjxjhm":"2024-2025学年秋","zcsm":"1-4周","cxjc":4,"xqh":"02","xqm":"东区","jxlh":"06","jxlm":"艺术学院楼","jash":"B405","jasm":"B405","kkxsh":"05","xsh":"05","jsm":"李彤","xb":"男","zcdm":"3","jysh":null,"bjh":"服设2205","xss":27,"bkskyl":8,"xf":"2","kslxdm":"02","kslxmc":"考查","kkxsm":"艺术","skxq":"3"},{"id":{"zxjxjhh":"2024-2025-1-1","jsh":"19974009","kxh":"01","kch":"10510522","skzc":"111100000000000000000000","skxq":4,"skjc":1},"kcm":"形象设计与应用k","jclxdm":"01","zxjxjhm":"2024-2025学年秋","zcsm":"1-4周","cxjc":4,"xqh":"02","xqm":"东区","jxlh":"06","jxlm":"艺术学院楼","jash":"B405","jasm":"B405","kkxsh":"05","xsh":"05","jsm":"李彤","xb":"男","zcdm":"3","jysh":null,"bjh":"服设2205","xss":27,"bkskyl":8,"xf":"2","kslxdm":"02","kslxmc":"考查","kkxsm":"艺术","skxq":"4"},{"id":{"zxjxjhh":"2024-2025-1-1","jsh":"20210043","kxh":"03","kch":"11711062A5","skzc":"000000001111000000000000","skxq":1,"skjc":5},"kcm":"形势与政策A5","jclxdm":"01","zxjxjhm":"2024-2025学年秋","zcsm":"9-12周","cxjc":2,"xqh":"02","xqm":"东区","jxlh":"20","jxlm":"第二公共教学楼","jash":"A409","jasm":"A409","kkxsh":"17","xsh":"17","jsm":"梁丹丹,胡英江","xb":null,"zcdm":"3","jysh":null,"bjh":"服设2205,环设2201,环设2202,环设2203","xss":115,"bkskyl":5,"xf":".25","kslxdm":"01","kslxmc":"考试","kkxsm":"马克思","skxq":"1"}]]